yz_doc/__init__.py
yz_doc/config.py
yz_doc/core/__init__.py
yz_doc/core/chunk.py
yz_doc/core/document.py
yz_doc/core/exceptions.py
yz_doc/loaders/__init__.py
yz_doc/loaders/aigc_loader.py
yz_doc/loaders/base.py
yz_doc/loaders/factory.py
yz_doc/loaders/feishu_loader.py
yz_doc/loaders/langchain_loader.py
yz_doc/splitters/__init__.py
yz_doc/splitters/base.py
yz_doc/splitters/factory.py
yz_doc/splitters/markdown_splitter.py
yz_doc/splitters/text_splitter.py
yz_doc/utils/__init__.py
yz_doc/utils/feishu_utils.py
yz_doc/utils/file_utils.py
yz_doc/utils/qiniu_utils.py
yz_doc/utils/request_utils.py
yz_doc-0.1.2.dist-info/METADATA
yz_doc-0.1.2.dist-info/WHEEL
yz_doc-0.1.2.dist-info/top_level.txt
yz_doc-0.1.2.dist-info/RECORD
