Metadata-Version: 2.4
Name: yz-doc
Version: 0.1.2
Summary: 有赞文档处理 SDK - 支持多格式文档加载与切分
Author-email: YouzanTech <tech@youzan.com>
License: MIT
Project-URL: Homepage, https://github.com/youzan/yz-doc
Project-URL: Documentation, https://github.com/youzan/yz-doc/blob/main/README.md
Project-URL: Repository, https://github.com/youzan/yz-doc.git
Project-URL: Issues, https://github.com/youzan/yz-doc/issues
Keywords: document,pdf,ocr,markdown,feishu,langchain,youzan
Classifier: Development Status :: 3 - Alpha
Classifier: Intended Audience :: Developers
Classifier: License :: OSI Approved :: MIT License
Classifier: Programming Language :: Python :: 3
Classifier: Programming Language :: Python :: 3.8
Classifier: Programming Language :: Python :: 3.9
Classifier: Programming Language :: Python :: 3.10
Classifier: Programming Language :: Python :: 3.11
Classifier: Programming Language :: Python :: 3.12
Requires-Python: >=3.8
Requires-Dist: yz-dubbo==0.1.4
Requires-Dist: langchain>=0.1.0
Requires-Dist: langchain-community>=0.1.0
Requires-Dist: langchain-text-splitters>=0.0.1
Requires-Dist: unstructured[all-docs]>=0.10.0
Requires-Dist: pymupdf4llm>=0.0.5
Requires-Dist: rapidocr-onnxruntime>=1.3.0
Requires-Dist: httpx>=0.24.0
Requires-Dist: python-magic-bin>=0.4.14; platform_system == "Windows"
Requires-Dist: python-magic>=0.4.27; platform_system != "Windows"
Provides-Extra: dev
Requires-Dist: pytest>=7.0.0; extra == "dev"
Requires-Dist: pytest-asyncio>=0.21.0; extra == "dev"
Requires-Dist: pytest-cov>=4.0.0; extra == "dev"
Requires-Dist: black>=23.0.0; extra == "dev"
Requires-Dist: flake8>=6.0.0; extra == "dev"
Requires-Dist: mypy>=1.0.0; extra == "dev"
Provides-Extra: ocr-paddle
Requires-Dist: paddleocr>=2.7.0; extra == "ocr-paddle"
Provides-Extra: layout
Requires-Dist: layoutparser>=0.3.4; extra == "layout"
Provides-Extra: feishu
Requires-Dist: lark-oapi>=1.2.0; extra == "feishu"
